unitmcp/__init__.py
unitmcp/__init__.py.bak
unitmcp/_version.py
unitmcp/_version.py.bak
unitmcp/__pycache__/__init__.cpython-311.pyc
unitmcp/__pycache__/__init__.cpython-312.pyc
unitmcp/__pycache__/__init__.cpython-313.pyc
unitmcp/ai/__init__.py
unitmcp/ai/common/model_interface.py
unitmcp/ai/llm/__init__.py
unitmcp/ai/llm/claude.py
unitmcp/ai/llm/ollama.py
unitmcp/ai/llm/openai.py
unitmcp/ai/nlp/__init__.py
unitmcp/ai/nlp/huggingface.py
unitmcp/ai/nlp/spacy_integration.py
unitmcp/ai/speech/__init__.py
unitmcp/ai/speech/audio_analysis.py
unitmcp/ai/speech/stt.py
unitmcp/ai/speech/tts.py
unitmcp/ai/vision/__init__.py
unitmcp/ai/vision/face_analysis.py
unitmcp/ai/vision/image_processing.py
unitmcp/ai/vision/object_detection.py
unitmcp/cli/__init__.py
unitmcp/cli/main.py
unitmcp/cli/parser.py
unitmcp/cli/__pycache__/__init__.cpython-311.pyc
unitmcp/cli/__pycache__/__init__.cpython-312.pyc
unitmcp/cli/__pycache__/main.cpython-311.pyc
unitmcp/cli/__pycache__/main.cpython-312.pyc
unitmcp/cli/__pycache__/parser.cpython-311.pyc
unitmcp/cli/__pycache__/parser.cpython-312.pyc
unitmcp/cli/commands/__init__.py
unitmcp/cli/commands/automation.py
unitmcp/cli/commands/device.py
unitmcp/cli/commands/nl.py
unitmcp/cli/commands/system.py
unitmcp/cli/commands/__pycache__/__init__.cpython-311.pyc
unitmcp/cli/commands/__pycache__/__init__.cpython-312.pyc
unitmcp/cli/commands/__pycache__/automation.cpython-311.pyc
unitmcp/cli/commands/__pycache__/automation.cpython-312.pyc
unitmcp/cli/commands/__pycache__/device.cpython-311.pyc
unitmcp/cli/commands/__pycache__/device.cpython-312.pyc
unitmcp/cli/commands/__pycache__/nl.cpython-311.pyc
unitmcp/cli/commands/__pycache__/nl.cpython-312.pyc
unitmcp/cli/commands/__pycache__/system.cpython-311.pyc
unitmcp/cli/commands/__pycache__/system.cpython-312.pyc
unitmcp/client/__init__.py
unitmcp/client/client.py
unitmcp/client/shell.py
unitmcp/client/__pycache__/__init__.cpython-311.pyc
unitmcp/client/__pycache__/__init__.cpython-312.pyc
unitmcp-0.1.69.dist-info/licenses/LICENSE
unitmcp-0.1.69.dist-info/METADATA
unitmcp-0.1.69.dist-info/WHEEL
unitmcp-0.1.69.dist-info/top_level.txt
unitmcp-0.1.69.dist-info/RECORD
