Metadata-Version: 2.4
Name: unitmcp
Version: 0.1.69
Summary: UnitMCP package for MCP hardware integration with Ollama LLM and Raspberry Pi hardware control.
Home-page: https://unitmcp.unitapi.com
Author: Tom Sapletta
Author-email: info@softreck.dev
Maintainer: unitmcp developers
Maintainer-email: info@softreck.dev
License: Apache-2.0
Keywords: python,unitmcp,streaming,real-time,annotation,processing
Classifier: Development Status :: 4 - Beta
Classifier: License :: OSI Approved :: Apache Software License
Classifier: Programming Language :: Python
Classifier: Programming Language :: Python :: 3
Classifier: Programming Language :: Python :: 3.7
Classifier: Programming Language :: Python :: 3.12
Classifier: Programming Language :: Python :: 3.13
Classifier: Topic :: Multimedia :: Video
Classifier: Topic :: Software Development :: Libraries :: Python Modules
Requires-Python: >=3.7.3
License-File: LICENSE
Requires-Dist: pyyaml>=6.0.1
Requires-Dist: psutil>=5.9.0
Requires-Dist: requests>=2.31.0
Requires-Dist: urllib3>=1.26.9
Requires-Dist: websockets>=10.3
Requires-Dist: aiohttp>=3.8.0
Requires-Dist: fastapi>=0.110.0
Requires-Dist: uvicorn>=0.27.0
Requires-Dist: acme>=4.0.0
Requires-Dist: cryptography>=42.0.0
Requires-Dist: certbot>=2.7.0
Requires-Dist: dnspython>=2.4.0
Requires-Dist: upnpclient>=1.0.3
Requires-Dist: zeroconf>=0.38.1
Requires-Dist: wsdiscovery>=2.0.0
Requires-Dist: onvif-zeep>=0.2.12
Requires-Dist: opencv-python>=4.5.0
Requires-Dist: pillow>=11.2.0
Requires-Dist: pyautogui>=0.9.50
Requires-Dist: pynput>=1.7.0
Requires-Dist: pyaudio>=0.2.11
Requires-Dist: sounddevice>=0.4.0
Requires-Dist: paramiko>=3.5.1
Requires-Dist: pytest>=8.3.5
Requires-Dist: pytest-cov>=4.1.0
Requires-Dist: pytest-asyncio==0.26.0
Requires-Dist: pytest-mock>=3.12.0
Requires-Dist: python-dotenv>=1.1.0
Requires-Dist: tabulate>=0.9.0
Requires-Dist: paho-mqtt>=1.6.0
Requires-Dist: asyncssh>=2.21.0
Dynamic: author-email
Dynamic: home-page
Dynamic: license-file
Dynamic: maintainer-email
Dynamic: requires-python
